django_musicbrainz_connector/__init__.py
django_musicbrainz_connector/admin.py
django_musicbrainz_connector/apps.py
django_musicbrainz_connector/routers.py
django_musicbrainz_connector/urls.py
django_musicbrainz_connector/utils.py
django_musicbrainz_connector/views.py
django_musicbrainz_connector/api/__init__.py
django_musicbrainz_connector/api/area.py
django_musicbrainz_connector/api/area_type.py
django_musicbrainz_connector/api/artist.py
django_musicbrainz_connector/api/artist_credit.py
django_musicbrainz_connector/api/artist_type.py
django_musicbrainz_connector/api/gender.py
django_musicbrainz_connector/api/language.py
django_musicbrainz_connector/api/link.py
django_musicbrainz_connector/api/link_attribute_type.py
django_musicbrainz_connector/api/link_type.py
django_musicbrainz_connector/api/medium.py
django_musicbrainz_connector/api/medium_format.py
django_musicbrainz_connector/api/recording.py
django_musicbrainz_connector/api/recording_work_link.py
django_musicbrainz_connector/api/release.py
django_musicbrainz_connector/api/release_group.py
django_musicbrainz_connector/api/release_group_primary_type.py
django_musicbrainz_connector/api/release_packaging.py
django_musicbrainz_connector/api/release_status.py
django_musicbrainz_connector/api/script.py
django_musicbrainz_connector/api/track.py
django_musicbrainz_connector/api/work.py
django_musicbrainz_connector/api/work_type.py
django_musicbrainz_connector/migrations/0001_initial.py
django_musicbrainz_connector/migrations/0002_work.py
django_musicbrainz_connector/migrations/0003_artistcredit_link_linktype_recording_and_more.py
django_musicbrainz_connector/migrations/0004_script.py
django_musicbrainz_connector/migrations/0005_language_alter_script_options.py
django_musicbrainz_connector/migrations/0006_releasepackaging.py
django_musicbrainz_connector/migrations/0007_releasestatus_alter_worktype_options.py
django_musicbrainz_connector/migrations/0008_releasegroup_releasegroupprimarytype.py
django_musicbrainz_connector-0.0.10.dist-info/LICENSE
django_musicbrainz_connector-0.0.10.dist-info/METADATA
django_musicbrainz_connector-0.0.10.dist-info/WHEEL
django_musicbrainz_connector-0.0.10.dist-info/top_level.txt
django_musicbrainz_connector-0.0.10.dist-info/RECORD
