Metadata-Version: 2.2
Name: django-musicbrainz-connector
Version: 0.0.10
Summary: A Django app that connects to a replica of the MusicBrainz database.
Home-page: https://github.com/mneia-gr/django-musicbrainz-connector
Author: Marios Zindilis
Author-email: marios@zindilis.com
License: BSD-3-Clause
Classifier: Environment :: Web Environment
Classifier: Framework :: Django
Classifier: Framework :: Django :: 5.2
Classifier: Intended Audience :: Developers
Classifier: License :: OSI Approved :: BSD License
Classifier: Operating System :: OS Independent
Classifier: Programming Language :: Python
Classifier: Programming Language :: Python :: 3
Classifier: Programming Language :: Python :: 3 :: Only
Classifier: Programming Language :: Python :: 3.10
Classifier: Programming Language :: Python :: 3.11
Classifier: Programming Language :: Python :: 3.12
Classifier: Topic :: Internet :: WWW/HTTP
Classifier: Topic :: Internet :: WWW/HTTP :: Dynamic Content
Requires-Python: >=3.10
License-File: LICENSE
Requires-Dist: Django>=5.2
Requires-Dist: djangorestframework>=3.15.2
Provides-Extra: test
Requires-Dist: flake8>=7.1.1; extra == "test"
Requires-Dist: black>=24.10.0; extra == "test"
Requires-Dist: isort>=5.13.2; extra == "test"
Requires-Dist: bandit>=1.8.2; extra == "test"
